odoo/addons/website_sale_product_minimal_price/README.rst
odoo/addons/website_sale_product_minimal_price/__init__.py
odoo/addons/website_sale_product_minimal_price/__manifest__.py
odoo/addons/website_sale_product_minimal_price/controllers/__init__.py
odoo/addons/website_sale_product_minimal_price/controllers/main.py
odoo/addons/website_sale_product_minimal_price/i18n/ca.po
odoo/addons/website_sale_product_minimal_price/i18n/es.po
odoo/addons/website_sale_product_minimal_price/i18n/nl.po
odoo/addons/website_sale_product_minimal_price/i18n/website_sale_product_minimal_price.pot
odoo/addons/website_sale_product_minimal_price/models/__init__.py
odoo/addons/website_sale_product_minimal_price/models/product_template.py
odoo/addons/website_sale_product_minimal_price/readme/CONFIGURE.rst
odoo/addons/website_sale_product_minimal_price/readme/CONTRIBUTORS.rst
odoo/addons/website_sale_product_minimal_price/readme/DESCRIPTION.rst
odoo/addons/website_sale_product_minimal_price/readme/USAGE.rst
odoo/addons/website_sale_product_minimal_price/static/description/icon.png
odoo/addons/website_sale_product_minimal_price/static/description/index.html
odoo/addons/website_sale_product_minimal_price/static/src/js/test_product_with_no_prices_tour.js
odoo/addons/website_sale_product_minimal_price/static/src/js/tour.js
odoo/addons/website_sale_product_minimal_price/static/src/js/website_sale_product_minimal_price.js
odoo/addons/website_sale_product_minimal_price/static/src/js/website_sale_product_price_scale.js
odoo/addons/website_sale_product_minimal_price/static/src/xml/website_sale_product_minimal_price.xml
odoo/addons/website_sale_product_minimal_price/static/src/xml/website_sale_product_price_scale.xml
odoo/addons/website_sale_product_minimal_price/tests/__init__.py
odoo/addons/website_sale_product_minimal_price/tests/test_product_with_no_prices.py
odoo/addons/website_sale_product_minimal_price/tests/test_website_sale_product_minimal_price.py
odoo13_addon_website_sale_product_minimal_price-13.0.1.1.1.dist-info/METADATA
odoo13_addon_website_sale_product_minimal_price-13.0.1.1.1.dist-info/WHEEL
odoo13_addon_website_sale_product_minimal_price-13.0.1.1.1.dist-info/top_level.txt
odoo13_addon_website_sale_product_minimal_price-13.0.1.1.1.dist-info/RECORD
